panoptes/__init__.py
panoptes/app.py
panoptes/database.py
panoptes/models.py
panoptes/panoptes.py
panoptes/schema_forms.py
panoptes/routes/__init__.py
panoptes/routes/api.py
panoptes/server_utilities/__init__.py
panoptes/server_utilities/db_queries.py
panoptes/static/__init__.py
panoptes/static/src/404.html
panoptes/static/src/__init__.py
panoptes/static/src/about.html
panoptes/static/src/index.html
panoptes/static/src/job.html
panoptes/static/src/searchResults.html
panoptes/static/src/workflow.html
panoptes/static/src/workflows.html
panoptes/static/src/css/style.css
panoptes/static/src/css/style.css.map
panoptes/static/src/css/style.min.css
panoptes/static/src/css/style.min.css.map
panoptes/static/src/img/favicon.ico
panoptes/static/src/img/avatars/1.jpg
panoptes/static/src/img/avatars/2.jpg
panoptes/static/src/img/avatars/3.jpg
panoptes/static/src/img/avatars/4.jpg
panoptes/static/src/img/avatars/5.jpg
panoptes/static/src/img/avatars/6.jpg
panoptes/static/src/img/avatars/7.jpg
panoptes/static/src/img/avatars/8.jpg
panoptes/static/src/img/brand/logo.svg
panoptes/static/src/img/brand/panoptes.png
panoptes/static/src/img/brand/panoptes.svg
panoptes/static/src/img/brand/panoptes_eye.png
panoptes/static/src/img/brand/panoptes_logo.svg
panoptes/static/src/img/brand/sygnet.svg
panoptes/static/src/js/charts.js
panoptes/static/src/js/charts.js.map
panoptes/static/src/js/colors.js
panoptes/static/src/js/colors.js.map
panoptes/static/src/js/main.js
panoptes/static/src/js/main.js.map
panoptes/static/src/js/popovers.js
panoptes/static/src/js/popovers.js.map
panoptes/static/src/js/tooltips.js
panoptes/static/src/js/tooltips.js.map
panoptes/static/src/js/widgets.js
panoptes/static/src/js/widgets.js.map
panoptes/static/src/js/src/charts.js
panoptes/static/src/js/src/colors.js
panoptes/static/src/js/src/init.js
panoptes/static/src/js/src/main.js
panoptes/static/src/js/src/popovers.js
panoptes/static/src/js/src/tooltips.js
panoptes/static/src/js/src/widgets.js
panoptes_ui-0.2.3.dist-info/LICENSE.md
panoptes_ui-0.2.3.dist-info/METADATA
panoptes_ui-0.2.3.dist-info/WHEEL
panoptes_ui-0.2.3.dist-info/entry_points.txt
panoptes_ui-0.2.3.dist-info/top_level.txt
panoptes_ui-0.2.3.dist-info/RECORD
