Metadata-Version: 2.1
Name: panoptes-ui
Version: 0.2.3
Summary: panoptes: monitor computational workflows in real time
Home-page: https://github.com/panoptes-organization/panoptes
Author: panoptes-organization
Author-email: georgekostoulas@gmail.com, agardelakos@gmail.com, fgypas@gmail.com, gntalaperas@gmail.com, dimitris.afe@gmail.com, rekoumisd@gmail.com, vsochat@stanford.edu
License: MIT
Classifier: Programming Language :: Python :: 3
Classifier: License :: OSI Approved :: MIT License
Classifier: Operating System :: OS Independent
License-File: LICENSE.md
Requires-Dist: flask >=1.1.1
Requires-Dist: humanfriendly >=4.18
Requires-Dist: marshmallow >=3.0.1
Requires-Dist: pytest >=5.3.0
Requires-Dist: requests >=2.22.0
Requires-Dist: SQLAlchemy >=1.3.7
